MANIFEST.in
README
setup.cfg
setup.py
lava/__init__.py
lava/celery/__init__.py
lava/celery/commands.py
lava/celery/config.py
lava/celery/queues.py
lava/celery/tasks.py
lava_celery.egg-info/PKG-INFO
lava_celery.egg-info/SOURCES.txt
lava_celery.egg-info/dependency_links.txt
lava_celery.egg-info/entry_points.txt
lava_celery.egg-info/namespace_packages.txt
lava_celery.egg-info/not-zip-safe
lava_celery.egg-info/requires.txt
lava_celery.egg-info/top_level.txt