Metadata-Version: 1.1
Name: lava-celery
Version: 0.3
Summary: Celery integration for LAVA Server
Home-page: UNKNOWN
Author: Zygmunt Krynicki
Author-email: zygmunt.krynicki@linaro.org
License: AGPL
Platform: UNKNOWN
Classifier: Development Status :: 3 - Alpha
Classifier: Intended Audience :: Developers
Classifier: License :: OSI Approved :: GNU Affero General Public License v3
Classifier: Operating System :: OS Independent
Classifier: Programming Language :: Python :: 2.6
Classifier: Programming Language :: Python :: 2.7
